sitemap_parser/__init__.py
sitemap_parser/loader.py
sitemap_parser/sitemap.py
sitemap_parser-0.0.8.dist-info/METADATA
sitemap_parser-0.0.8.dist-info/WHEEL
sitemap_parser-0.0.8.dist-info/top_level.txt
sitemap_parser-0.0.8.dist-info/RECORD
