Metadata-Version: 2.1
Name: sitemap-parser
Version: 0.0.8
Summary: UNKNOWN
Home-page: https://github.com/KokocGroup/sitemap_parser
Author: Evgeniy Titov
Author-email: falgore88@gmail.com
License: UNKNOWN
Platform: UNKNOWN
Requires-Dist: beautifulsoup4 (==4.6.3)
Requires-Dist: lxml (==4.2.5)
